Zeitzono/ZeitzonoCities.py
Zeitzono/ZeitzonoCity.py
Zeitzono/ZeitzonoDB.py
Zeitzono/ZeitzonoMain.py
Zeitzono/ZeitzonoSearch.py
Zeitzono/ZeitzonoTime.py
Zeitzono/ZeitzonoUrwidHelp.py
Zeitzono/ZeitzonoUrwidMain.py
Zeitzono/ZeitzonoUrwidPalette.py
Zeitzono/ZeitzonoUrwidSearch.py
Zeitzono/ZeitzonoUrwidSplashScreen.py
Zeitzono/ZeitzonoWidgetSwitcher.py
Zeitzono/__init__.py
Zeitzono/data/helpmain.txt
Zeitzono/data/helpsearch.txt
Zeitzono/data/zeitzono.db
zeitzono-0.9.3.data/data/share/doc/zeitzono/LICENSE
zeitzono-0.9.3.data/data/share/doc/zeitzono/LICENSE-geonames-db
zeitzono-0.9.3.data/data/share/doc/zeitzono/README
zeitzono-0.9.3.data/data/share/man/man1/zeitzono.1
zeitzono-0.9.3.dist-info/licenses/LICENSE
zeitzono-0.9.3.dist-info/licenses/LICENSE-geonames-db
zeitzono-0.9.3.dist-info/METADATA
zeitzono-0.9.3.dist-info/WHEEL
zeitzono-0.9.3.dist-info/entry_points.txt
zeitzono-0.9.3.dist-info/top_level.txt
zeitzono-0.9.3.dist-info/RECORD
