Metadata-Version: 2.4
Name: zeitzono
Version: 0.9.3
Summary: city based timezone converter with a curses (TUI) interface
Home-page: https://zeitzono.org/
Author: N.J. Thomas
Author-email: info@zeitzono.org
License: BSD
Keywords: console,curses,time,zone,timezone,convert,conversion,city,cities
Platform: POSIX
Classifier: Development Status :: 3 - Alpha
Classifier: Environment :: Console
Classifier: Environment :: Console :: Curses
Classifier: Intended Audience :: Other Audience
Classifier: Intended Audience :: System Administrators
Classifier: License :: OSI Approved :: BSD License
Classifier: Operating System :: POSIX
Classifier: Operating System :: Unix
Classifier: Programming Language :: Python :: 3
Classifier: Topic :: Office/Business :: Scheduling
Classifier: Topic :: Utilities
Requires-Python: >3.9.0
License-File: LICENSE
License-File: LICENSE-geonames-db
Requires-Dist: python-dateutil
Requires-Dist: parsedatetime
Requires-Dist: pytz
Requires-Dist: tzlocal
Requires-Dist: urwid
Requires-Dist: xdg
Dynamic: author
Dynamic: author-email
Dynamic: classifier
Dynamic: description
Dynamic: description-content-type
Dynamic: home-page
Dynamic: keywords
Dynamic: license
Dynamic: license-file
Dynamic: platform
Dynamic: requires-dist
Dynamic: requires-python
Dynamic: summary
